LICENSE
meliorateapp/main.py
meliorateapp-0.1.0.dist-info/entry_points.txt
meliorateapp-0.1.0.dist-info/LICENSE
meliorateapp-0.1.0.dist-info/WHEEL
meliorateapp-0.1.0.dist-info/METADATA
meliorateapp-0.1.0.dist-info/RECORD
