Metadata-Version: 2.1
Name: meliorateapp
Version: 0.1.0
Summary: A code generator and test runner for C++
Home-page: https://github.com/diwalkerdev/Meliorate
Keywords: cpp,unit-testing,poetry,python,linux,windows,macos
Author: David Walker
Author-email: diwalkerdev@twitter.com
Requires-Python: >=3.8,<4.0
Classifier: Development Status :: 3 - Alpha
Classifier: Environment :: Console
Classifier: Intended Audience :: Developers
Classifier: Intended Audience :: End Users/Desktop
Classifier: License :: OSI Approved :: Mozilla Public License 2.0 (MPL 2.0)
Classifier: Operating System :: OS Independent
Classifier: Programming Language :: Python :: 3
Classifier: Programming Language :: Python :: 3.7
Classifier: Programming Language :: Python :: 3.8
Classifier: Topic :: Software Development :: Code Generators
Classifier: Topic :: Software Development :: Testing
Requires-Dist: clang (>=6.0.0,<7.0.0)
Requires-Dist: jinja2 (>=2.11.2,<3.0.0)
Project-URL: Repository, https://github.com/diwalkerdev/Meliorate
